{
  "generatedAt": "2026-02-16T08:45:30.678Z",
  "projectPath": "/Users/rl/Nutstore_Files/my_nutstore/520-program/muxvo",
  "totalApis": 7,
  "scannedFiles": 203,
  "categories": {
    "API 服务": [
      {
        "path": "{成员访问}",
        "method": "GET",
        "file": "main/services/chat-sync.ts",
        "line": 48,
        "functionName": "mirrorMap.get",
        "params": [],
        "responseFields": [],
        "category": "API 服务"
      },
      {
        "path": "{变量:path}",
        "method": "GET",
        "file": "main/services/data-sync/sync-manager.ts",
        "line": 99,
        "functionName": "lockedFiles.get",
        "params": [],
        "responseFields": [],
        "category": "API 服务"
      },
      {
        "path": "{变量:id}",
        "method": "GET",
        "file": "main/services/terminal/manager.ts",
        "line": 96,
        "functionName": "outputBuffers.get",
        "params": [],
        "responseFields": [],
        "category": "API 服务"
      },
      {
        "path": "{变量:id}",
        "method": "DELETE",
        "file": "main/services/terminal/manager.ts",
        "line": 124,
        "functionName": "terminals.delete",
        "params": [],
        "responseFields": [],
        "category": "API 服务"
      }
    ],
    "modules": [
      {
        "path": "{变量:event}",
        "method": "GET",
        "file": "modules/marketplace/directory-watcher.ts",
        "line": 23,
        "functionName": "listeners.get",
        "params": [],
        "responseFields": [],
        "category": "modules"
      },
      {
        "path": "change",
        "method": "GET",
        "file": "modules/marketplace/directory-watcher.ts",
        "line": 28,
        "functionName": "listeners.get",
        "params": [],
        "responseFields": [],
        "category": "modules"
      },
      {
        "path": "{变量:key}",
        "method": "GET",
        "file": "modules/score/cache.ts",
        "line": 37,
        "functionName": "store.get",
        "params": [],
        "responseFields": [],
        "category": "modules"
      }
    ]
  },
  "apis": [
    {
      "path": "{成员访问}",
      "method": "GET",
      "file": "main/services/chat-sync.ts",
      "line": 48,
      "functionName": "mirrorMap.get",
      "params": [],
      "responseFields": [],
      "category": "API 服务"
    },
    {
      "path": "{变量:path}",
      "method": "GET",
      "file": "main/services/data-sync/sync-manager.ts",
      "line": 99,
      "functionName": "lockedFiles.get",
      "params": [],
      "responseFields": [],
      "category": "API 服务"
    },
    {
      "path": "{变量:id}",
      "method": "GET",
      "file": "main/services/terminal/manager.ts",
      "line": 96,
      "functionName": "outputBuffers.get",
      "params": [],
      "responseFields": [],
      "category": "API 服务"
    },
    {
      "path": "{变量:id}",
      "method": "DELETE",
      "file": "main/services/terminal/manager.ts",
      "line": 124,
      "functionName": "terminals.delete",
      "params": [],
      "responseFields": [],
      "category": "API 服务"
    },
    {
      "path": "{变量:event}",
      "method": "GET",
      "file": "modules/marketplace/directory-watcher.ts",
      "line": 23,
      "functionName": "listeners.get",
      "params": [],
      "responseFields": [],
      "category": "modules"
    },
    {
      "path": "change",
      "method": "GET",
      "file": "modules/marketplace/directory-watcher.ts",
      "line": 28,
      "functionName": "listeners.get",
      "params": [],
      "responseFields": [],
      "category": "modules"
    },
    {
      "path": "{变量:key}",
      "method": "GET",
      "file": "modules/score/cache.ts",
      "line": 37,
      "functionName": "store.get",
      "params": [],
      "responseFields": [],
      "category": "modules"
    }
  ]
}